LICENSE
MANIFEST.in
README.md
lgpl-3.0.txt
setup.cfg
setup.py
src/pipl/__init__.py
src/pipl/__main__.py
src/pipl/autopack.py
src/pipl/main.py
src/pipl/packl.py
src/pipl/project.py
src/pipl/utils.py
src/pipl/workspace.py
src/pipl.egg-info/PKG-INFO
src/pipl.egg-info/SOURCES.txt
src/pipl.egg-info/dependency_links.txt
src/pipl.egg-info/entry_points.txt
src/pipl.egg-info/requires.txt
src/pipl.egg-info/top_level.txt