Metadata-Version: 2.1
Name: pipl
Version: 0.2.0.dev3
Summary: Package Index PipeLine
Home-page: https://gitlab.com/open-minds-group/pipl
Author: Damien "dee" Coureau
Author-email: dee909@gmail.com
License: LGPLv3+
Keywords: pipeline dataflow dependency asset
Platform: UNKNOWN
Classifier: Development Status :: 1 - Planning
Classifier: Topic :: Desktop Environment :: File Managers
Classifier: Intended Audience :: End Users/Desktop
Classifier: Intended Audience :: Information Technology
Classifier: Operating System :: OS Independent
Classifier: Programming Language :: Python :: 2.7
Classifier: Programming Language :: Python :: 3.6
Classifier: License :: OSI Approved :: GNU Lesser General Public License v3 or later (LGPLv3+)
Requires-Python: >=2.7,!=3.0.*,!=3.1.*,!=3.2.*
